pandas2-setup.py
pandas2/__init__.py
pandas2.egg-info/PKG-INFO
pandas2.egg-info/SOURCES.txt
pandas2.egg-info/__init__.py
pandas2.egg-info/dependency_links.txt
pandas2.egg-info/top_level.txt