Metadata-Version: 1.1
Name: pandas2
Version: 0.0.0
Summary: pandas2
Home-page: http://github.com/pandas-dev/pandas2
Author: Wes McKinney
Author-email: wesmckinn@gmail.com
License: Apache License, Version 2.0
Platform: UNKNOWN
Classifier: Development Status :: 1 - Planning
Classifier: Operating System :: OS Independent
Classifier: Intended Audience :: Science/Research
Classifier: Programming Language :: Python
Classifier: Programming Language :: Python :: 3
Classifier: Topic :: Scientific/Engineering
